verifyid/__init__.py
verifyid/client.py
verifyid_sdk_python-1.0.4.dist-info/licenses/LICENSE
verifyid_sdk_python-1.0.4.dist-info/METADATA
verifyid_sdk_python-1.0.4.dist-info/WHEEL
verifyid_sdk_python-1.0.4.dist-info/top_level.txt
verifyid_sdk_python-1.0.4.dist-info/RECORD
