Metadata-Version: 2.4
Name: verifyid-sdk-python
Version: 1.0.4
Summary: Official Python SDK for VerifyID.io KYC, AML, Biometric and Document Verification APIs.
Home-page: https://github.com/OmniSolInfoTech/verifyid-sdk-python
Author: Philip Csaplar
Author-email: your@email.com
License: MIT
Classifier: Programming Language :: Python :: 3
Classifier: License :: OSI Approved :: MIT License
Classifier: Operating System :: OS Independent
Classifier: Development Status :: 5 - Production/Stable
Classifier: Intended Audience :: Developers
Classifier: Topic :: Software Development :: Libraries
Requires-Python: >=3.7
License-File: LICENSE
Requires-Dist: requests>=2.20.0
Dynamic: author
Dynamic: author-email
Dynamic: classifier
Dynamic: description
Dynamic: description-content-type
Dynamic: home-page
Dynamic: license
Dynamic: license-file
Dynamic: requires-dist
Dynamic: requires-python
Dynamic: summary
